{"frames":{"solidSkin/pourDot":{"frame":{"x":2,"y":2,"w":96,"h":88},"rotated":false,"trimmed":false,"spriteSourceSize":{"x":0,"y":0,"w":96,"h":88},"sourceSize":{"w":96,"h":88}},"solidSkin/pourFore":{"frame":{"x":100,"y":2,"w":8,"h":264},"rotated":false,"trimmed":false,"spriteSourceSize":{"x":0,"y":0,"w":8,"h":264},"sourceSize":{"w":8,"h":264}},"solidSkin/pourLen":{"frame":{"x":110,"y":2,"w":8,"h":264},"rotated":false,"trimmed":false,"spriteSourceSize":{"x":0,"y":0,"w":8,"h":264},"sourceSize":{"w":8,"h":264}}},"meta":{"app":"Adobe Animate","version":"22.0.5.191","image":"solidSkin9178cd6e700dee4b7eef75489b9dc63e.png","format":"RGBA8888","size":{"w":128,"h":512},"scale":"1"}}